wagtail_mfa/__init__.py
wagtail_mfa/forms.py
wagtail_mfa/settings.py
wagtail_mfa/utils.py
wagtail_mfa/views.py
wagtail_mfa/wagtail_hooks.py
wagtail_mfa/locale/nl/LC_MESSAGES/django.mo
wagtail_mfa/locale/nl/LC_MESSAGES/django.po
wagtail_mfa/static/wagtail_mfa/wagtail_mfa.css
wagtail_mfa/static/wagtail_mfa/wagtail_mfa.css.map
wagtail_mfa/static/wagtail_mfa/wagtail_mfa.js
wagtail_mfa/static/wagtail_mfa/wagtail_mfa.js.map
wagtail_mfa/static/wagtail_mfa/wagtailadmin_login.css
wagtail_mfa/static/wagtail_mfa/wagtailadmin_login.css.map
wagtail_mfa/static/wagtail_mfa/wagtailadmin_login.js
wagtail_mfa/templates/wagtail_mfa/base_admin.html
wagtail_mfa/templates/wagtail_mfa/registered_devices_list.html
wagtail_mfa/templates/wagtail_mfa/_compat/render_field_wagtail52.html
wagtail_mfa/templates/wagtail_mfa/_compat/render_field_wagtail60.html
wagtail_mfa/templates/wagtail_mfa/icons/passkey.svg
wagtail_mfa/templates/wagtail_mfa/webauthn/create.html
wagtail_mfa/templates/wagtail_mfa/webauthn/delete.html
wagtail_mfa/templates/wagtail_mfa/webauthn/edit.html
wagtail_mfa/templates/wagtailadmin/login.html
wagtail_mfa/templatetags/__init__.py
wagtail_mfa/templatetags/wagtail_mfa_tags.py
wagtail_mfa-0.1.0.dist-info/METADATA
wagtail_mfa-0.1.0.dist-info/WHEEL
wagtail_mfa-0.1.0.dist-info/licenses/LICENSE
wagtail_mfa-0.1.0.dist-info/RECORD
