Metadata-Version: 2.3
Name: wagtail-mfa
Version: 0.1.0
Summary: Secure your Wagtail site with multi-factor authentication. Supports TOTP and WebAuthn/Passkeys.
Project-URL: Changelog, https://github.com/Stormbase/wagtail-mfa/blob/main/CHANGELOG.md
Project-URL: Issues, https://github.com/Stormbase/wagtail-mfa/issues
Project-URL: Source, https://github.com/Stormbase/wagtail-mfa
Author-email: "Storm B. Heg" <storm@stormbase.digital>
License-Expression: BSD-3-Clause
License-File: LICENSE
Keywords: 2fa,mfa,passkeys,security,totp,wagtail,webauthn
Classifier: Development Status :: 3 - Alpha
Classifier: Environment :: Web Environment
Classifier: Framework :: Django
Classifier: Framework :: Django :: 4.2
Classifier: Framework :: Django :: 5.0
Classifier: Framework :: Wagtail
Classifier: Framework :: Wagtail :: 5
Classifier: Framework :: Wagtail :: 6
Classifier: Intended Audience :: Developers
Classifier: License :: OSI Approved :: BSD License
Classifier: Operating System :: OS Independent
Classifier: Programming Language :: Python
Classifier: Programming Language :: Python :: 3.9
Classifier: Programming Language :: Python :: 3.10
Classifier: Programming Language :: Python :: 3.11
Classifier: Programming Language :: Python :: 3.12
Classifier: Topic :: Security
Requires-Python: >=3.9
Requires-Dist: django-otp-webauthn<1.0,>=0.1.0
Requires-Dist: django-otp<2.0,>=1.0
Requires-Dist: django>=4.2
Requires-Dist: precis-i18n<2.0,>=1.1.0
Requires-Dist: wagtail>=5.2
